[
  {
    "name": "Refined Jacket",
    "description": "The Persevering actuating leverage Chicken offers reliable performance and well-documented design",
    "sku": "IX0PSH5BOK",
    "brand": "Lesch - Fay",
    "category": "Clothing",
    "price": 876.49,
    "price_min": 845.49,
    "stock": 481,
    "color": "yellow",
    "size": "Large",
    "image_url": "https://images.unsplash.com/photo-1548624313-0396c75e4b1a?crop=entropy&cs=tinysrgb&fit=max&fm=jpg&ixid=M3w4MDQ0NzJ8MHwxfHNlYXJjaHwxNHx8SmFja2V0fGVufDB8fHx8MTc1Nzk0OTU1MXww&ixlib=rb-4.1.0&q=80&w=400"
  },
  {
    "name": "Gorgeous Camera",
    "description": "The white Soap combines Kazakhstan aesthetics with Calcium-based durability",
    "sku": "T04ZNYA4D8",
    "brand": "Champlin LLC",
    "category": "Electronics & Home Appliances",
    "price": 1038.29,
    "price_min": 988.29,
    "stock": 95,
    "color": "white",
    "size": "Large",
    "image_url": "https://images.unsplash.com/photo-1512790182412-b19e6d62bc39?crop=entropy&cs=tinysrgb&fit=max&fm=jpg&ixid=M3w4MDQ0NzJ8MHwxfHNlYXJjaHwxNHx8Q2FtZXJhfGVufDB8fHx8MTc1Nzk0OTU1Mnww&ixlib=rb-4.1.0&q=80&w=400"
  },
  {
    "name": "Bespoke Sofa",
    "description": "Discover the bear-like agility of our Sausages, perfect for heavy users",
    "sku": "35VGCA0OMF",
    "brand": "Hoeger - Greenholt",
    "category": "Furniture",
    "price": 563.79,
    "price_min": 546.79,
    "stock": 472,
    "color": "teal",
    "size": "Small",
    "image_url": "https://images.unsplash.com/photo-1540574163026-643ea20ade25?crop=entropy&cs=tinysrgb&fit=max&fm=jpg&ixid=M3w4MDQ0NzJ8MHwxfHNlYXJjaHwyfHxTb2ZhfGVufDB8fHx8MTc1Nzk0OTU1MXww&ixlib=rb-4.1.0&q=80&w=400"
  },
  {
    "name": "Generic Shoes",
    "description": "Practical Bike designed with Gold for shallow performance",
    "sku": "Y4TVPKDBMG",
    "brand": "White, Bogan and Russel",
    "category": "Clothing",
    "price": 367.15,
    "price_min": 358.15,
    "stock": 395,
    "color": "cyan",
    "size": "Large",
    "image_url": "https://images.unsplash.com/photo-1603808033192-082d6919d3e1?crop=entropy&cs=tinysrgb&fit=max&fm=jpg&ixid=M3w4MDQ0NzJ8MHwxfHNlYXJjaHwxOXx8U2hvZXN8ZW58MHx8fHwxNzU3OTQ5NTUxfDA&ixlib=rb-4.1.0&q=80&w=400"
  },
  {
    "name": "Gorgeous Refrigerator",
    "description": "Savor the savory essence in our Shirt, designed for rewarding culinary adventures",
    "sku": "NBU50RGQ0N",
    "brand": "Blanda, Herzog and Wilkinson",
    "category": "Electronics & Home Appliances",
    "price": 1870.06,
    "price_min": 1831.06,
    "stock": 25,
    "color": "purple",
    "size": "Medium",
    "image_url": "https://images.unsplash.com/photo-1588854337115-1c67d9247e4d?crop=entropy&cs=tinysrgb&fit=max&fm=jpg&ixid=M3w4MDQ0NzJ8MHwxfHNlYXJjaHw5fHxSZWZyaWdlcmF0b3J8ZW58MHx8fHwxNzU3OTQ5NTUxfDA&ixlib=rb-4.1.0&q=80&w=400"
  },
  {
    "name": "Awesome Shirt",
    "description": "Featuring Osmium-enhanced technology, our Bike offers unparalleled deficient performance",
    "sku": "L0PBOKUMS5",
    "brand": "Sipes Inc",
    "category": "Clothing",
    "price": 1037.19,
    "price_min": 1003.19,
    "stock": 201,
    "color": "magenta",
    "size": "Large",
    "image_url": "https://images.unsplash.com/photo-1618354691373-d851c5c3a990?crop=entropy&cs=tinysrgb&fit=max&fm=jpg&ixid=M3w4MDQ0NzJ8MHwxfHNlYXJjaHw0fHxTaGlydHxlbnwwfHx8fDE3NTc5NDk1NTF8MA&ixlib=rb-4.1.0&q=80&w=400"
  },
  {
    "name": "Sleek Pants",
    "description": "The sleek and lone Tuna comes with lime LED lighting for smart functionality",
    "sku": "VS65YTTO55",
    "brand": "Cummerata Inc",
    "category": "Clothing",
    "price": 80.29,
    "price_min": 65.29,
    "stock": 338,
    "color": "yellow",
    "size": "Small",
    "image_url": "https://images.unsplash.com/photo-1548883354-7622d03aca27?crop=entropy&cs=tinysrgb&fit=max&fm=jpg&ixid=M3w4MDQ0NzJ8MHwxfHNlYXJjaHwxM3x8UGFudHN8ZW58MHx8fHwxNzU3OTQ5NTUxfDA&ixlib=rb-4.1.0&q=80&w=400"
  },
  {
    "name": "Ergonomic Shirt",
    "description": "The Reverse-engineered incremental moderator Chicken offers reliable performance and vast design",
    "sku": "XZX6FZ1Q1Y",
    "brand": "Orn Inc",
    "category": "Clothing",
    "price": 844.86,
    "price_min": 838.86,
    "stock": 328,
    "color": "ivory",
    "size": "Large",
    "image_url": "https://images.unsplash.com/photo-1596755094514-f87e34085b2c?crop=entropy&cs=tinysrgb&fit=max&fm=jpg&ixid=M3w4MDQ0NzJ8MHwxfHNlYXJjaHwxfHxTaGlydHxlbnwwfHx8fDE3NTc5NDk1NTF8MA&ixlib=rb-4.1.0&q=80&w=400"
  },
  {
    "name": "Handcrafted Laptop",
    "description": "Experience the magenta brilliance of our Gloves, perfect for scornful environments",
    "sku": "UKFP52PVAL",
    "brand": "Rice, Welch and Jacobi",
    "category": "Electronics & Home Appliances",
    "price": 1066.89,
    "price_min": 1022.8900000000001,
    "stock": 41,
    "color": "grey",
    "size": "Medium",
    "image_url": "https://images.unsplash.com/photo-1541807084-5c52b6b3adef?crop=entropy&cs=tinysrgb&fit=max&fm=jpg&ixid=M3w4MDQ0NzJ8MHwxfHNlYXJjaHw5fHxMYXB0b3B8ZW58MHx8fHwxNzU3OTQ5NTUxfDA&ixlib=rb-4.1.0&q=80&w=400"
  },
  {
    "name": "Refined Microwave",
    "description": "The silver Chips combines Montserrat aesthetics with Nobelium-based durability",
    "sku": "9T6XTC89L0",
    "brand": "Turcotte - Champlin",
    "category": "Electronics & Home Appliances",
    "price": 555.05,
    "price_min": 550.05,
    "stock": 70,
    "color": "blue",
    "size": "Medium",
    "image_url": "https://images.unsplash.com/photo-1574269909862-7e1d70bb8078?crop=entropy&cs=tinysrgb&fit=max&fm=jpg&ixid=M3w4MDQ0NzJ8MHwxfHNlYXJjaHw2fHxNaWNyb3dhdmV8ZW58MHx8fHwxNzU3OTQ5NTUxfDA&ixlib=rb-4.1.0&q=80&w=400"
  },
  {
    "name": "Fantastic Jacket",
    "description": "Innovative Pizza featuring brave technology and Plastic construction",
    "sku": "91JSWYG0BM",
    "brand": "Koelpin LLC",
    "category": "Clothing",
    "price": 199.19,
    "price_min": 159.19,
    "stock": 211,
    "color": "sky blue",
    "size": "Medium",
    "image_url": "https://images.unsplash.com/photo-1521223890158-f9f7c3d5d504?crop=entropy&cs=tinysrgb&fit=max&fm=jpg&ixid=M3w4MDQ0NzJ8MHwxfHNlYXJjaHwzfHxKYWNrZXR8ZW58MHx8fHwxNzU3OTQ5NTUxfDA&ixlib=rb-4.1.0&q=80&w=400"
  },
  {
    "name": "Frozen Desk",
    "description": "Featuring Niobium-enhanced technology, our Car offers unparalleled upset performance",
    "sku": "RMM0ZCZK1X",
    "brand": "Ratke, Lockman and Hintz",
    "category": "Furniture",
    "price": 1808.49,
    "price_min": 1773.49,
    "stock": 94,
    "color": "black",
    "size": "Medium",
    "image_url": "https://images.unsplash.com/photo-1535957998253-26ae1ef29506?crop=entropy&cs=tinysrgb&fit=max&fm=jpg&ixid=M3w4MDQ0NzJ8MHwxfHNlYXJjaHw1fHxEZXNrfGVufDB8fHx8MTc1Nzk0OTU1MXww&ixlib=rb-4.1.0&q=80&w=400"
  },
  {
    "name": "Small Laptop",
    "description": "Experience the tan brilliance of our Tuna, perfect for shallow environments",
    "sku": "9IRW3QTTNF",
    "brand": "Ortiz - Heidenreich",
    "category": "Electronics & Home Appliances",
    "price": 1842.29,
    "price_min": 1819.29,
    "stock": 148,
    "color": "pink",
    "size": "Small",
    "image_url": "https://images.unsplash.com/photo-1516387938699-a93567ec168e?crop=entropy&cs=tinysrgb&fit=max&fm=jpg&ixid=M3w4MDQ0NzJ8MHwxfHNlYXJjaHwxNnx8TGFwdG9wfGVufDB8fHx8MTc1Nzk0OTU1MXww&ixlib=rb-4.1.0&q=80&w=400"
  },
  {
    "name": "Licensed Shirt",
    "description": "Discover the colorless new Pants with an exciting mix of Ceramic ingredients",
    "sku": "70ZBHYMTGH",
    "brand": "Gutmann - Lubowitz",
    "category": "Clothing",
    "price": 1464.59,
    "price_min": 1414.59,
    "stock": 421,
    "color": "sky blue",
    "size": "Large",
    "image_url": "https://images.unsplash.com/photo-1607345366928-199ea26cfe3e?crop=entropy&cs=tinysrgb&fit=max&fm=jpg&ixid=M3w4MDQ0NzJ8MHwxfHNlYXJjaHw3fHxTaGlydHxlbnwwfHx8fDE3NTc5NDk1NTF8MA&ixlib=rb-4.1.0&q=80&w=400"
  },
  {
    "name": "Unbranded Jacket",
    "description": "New Table model with 96 GB RAM, 402 GB storage, and lean features",
    "sku": "V5YSG1E3DW",
    "brand": "Goodwin and Sons",
    "category": "Clothing",
    "price": 119.49,
    "price_min": 109.49,
    "stock": 288,
    "color": "violet",
    "size": "Large",
    "image_url": "https://images.unsplash.com/photo-1544022613-e87ca75a784a?crop=entropy&cs=tinysrgb&fit=max&fm=jpg&ixid=M3w4MDQ0NzJ8MHwxfHNlYXJjaHw3fHxKYWNrZXR8ZW58MHx8fHwxNzU3OTQ5NTUxfDA&ixlib=rb-4.1.0&q=80&w=400"
  },
  {
    "name": "Frozen Chair",
    "description": "Our ostrich-friendly Table ensures confused comfort for your pets",
    "sku": "5HGZXVRBZ1",
    "brand": "Smith, Lubowitz and Mueller",
    "category": "Furniture",
    "price": 799.45,
    "price_min": 782.45,
    "stock": 372,
    "color": "gold",
    "size": "Large",
    "image_url": "https://images.unsplash.com/photo-1505843490538-5133c6c7d0e1?crop=entropy&cs=tinysrgb&fit=max&fm=jpg&ixid=M3w4MDQ0NzJ8MHwxfHNlYXJjaHwxMHx8Q2hhaXJ8ZW58MHx8fHwxNzU3OTQ5NTUxfDA&ixlib=rb-4.1.0&q=80&w=400"
  },
  {
    "name": "Practical Desk",
    "description": "The sleek and overcooked Table comes with blue LED lighting for smart functionality",
    "sku": "ZAQW5PDCN5",
    "brand": "Daniel, Quitzon and Mills",
    "category": "Furniture",
    "price": 1020.99,
    "price_min": 1004.99,
    "stock": 31,
    "color": "orange",
    "size": "Medium",
    "image_url": "https://images.unsplash.com/photo-1493934558415-9d19f0b2b4d2?crop=entropy&cs=tinysrgb&fit=max&fm=jpg&ixid=M3w4MDQ0NzJ8MHwxfHNlYXJjaHwxMXx8RGVza3xlbnwwfHx8fDE3NTc5NDk1NTF8MA&ixlib=rb-4.1.0&q=80&w=400"
  },
  {
    "name": "Gorgeous Dress",
    "description": "Ergonomic Cheese made with Bronze for all-day pessimistic support",
    "sku": "SD7YLDAEM2",
    "brand": "Greenfelder, Ruecker and Abernathy",
    "category": "Clothing",
    "price": 1693.25,
    "price_min": 1662.25,
    "stock": 24,
    "color": "maroon",
    "size": "Small",
    "image_url": "https://images.unsplash.com/photo-1496747611176-843222e1e57c?crop=entropy&cs=tinysrgb&fit=max&fm=jpg&ixid=M3w4MDQ0NzJ8MHwxfHNlYXJjaHw5fHxEcmVzc3xlbnwwfHx8fDE3NTc5NDk1NTF8MA&ixlib=rb-4.1.0&q=80&w=400"
  },
  {
    "name": "Oriental Pants",
    "description": "Professional-grade Shirt perfect for right training and recreational use",
    "sku": "YZNQ2NAM4V",
    "brand": "Mann, Kshlerin and O'Reilly",
    "category": "Clothing",
    "price": 1058.89,
    "price_min": 1012.8900000000001,
    "stock": 371,
    "color": "white",
    "size": "Large",
    "image_url": "https://images.unsplash.com/photo-1605518216938-7c31b7b14ad0?crop=entropy&cs=tinysrgb&fit=max&fm=jpg&ixid=M3w4MDQ0NzJ8MHwxfHNlYXJjaHwxNHx8UGFudHN8ZW58MHx8fHwxNzU3OTQ5NTUxfDA&ixlib=rb-4.1.0&q=80&w=400"
  },
  {
    "name": "Sleek Desk",
    "description": "Stylish Chicken designed to make you stand out with snappy looks",
    "sku": "VWX6CAPUU5",
    "brand": "Hudson LLC",
    "category": "Furniture",
    "price": 717.15,
    "price_min": 685.15,
    "stock": 442,
    "color": "indigo",
    "size": "Medium",
    "image_url": "https://images.unsplash.com/photo-1505330622279-bf7d7fc918f4?crop=entropy&cs=tinysrgb&fit=max&fm=jpg&ixid=M3w4MDQ0NzJ8MHwxfHNlYXJjaHw3fHxEZXNrfGVufDB8fHx8MTc1Nzk0OTU1MXww&ixlib=rb-4.1.0&q=80&w=400"
  },
  {
    "name": "Recycled Jacket",
    "description": "Our squirrel-friendly Mouse ensures genuine comfort for your pets",
    "sku": "ONWLFWIEP0",
    "brand": "Greenholt, Nienow and Pollich",
    "category": "Clothing",
    "price": 558.9,
    "price_min": 544.9,
    "stock": 173,
    "color": "gold",
    "size": "Large",
    "image_url": "https://images.unsplash.com/photo-1552327359-d86398116072?crop=entropy&cs=tinysrgb&fit=max&fm=jpg&ixid=M3w4MDQ0NzJ8MHwxfHNlYXJjaHw2fHxKYWNrZXR8ZW58MHx8fHwxNzU3OTQ5NTUxfDA&ixlib=rb-4.1.0&q=80&w=400"
  },
  {
    "name": "Elegant Bed",
    "description": "Professional-grade Car perfect for oval training and recreational use",
    "sku": "JPQPT7MIAK",
    "brand": "Labadie Group",
    "category": "Furniture",
    "price": 1373.49,
    "price_min": 1328.49,
    "stock": 157,
    "color": "silver",
    "size": "Small",
    "image_url": "https://images.unsplash.com/photo-1547211374-f44a1cfce7aa?crop=entropy&cs=tinysrgb&fit=max&fm=jpg&ixid=M3w4MDQ0NzJ8MHwxfHNlYXJjaHwxOHx8QmVkfGVufDB8fHx8MTc1Nzk0OTU1MXww&ixlib=rb-4.1.0&q=80&w=400"
  },
  {
    "name": "Gorgeous Shirt",
    "description": "The Customizable scalable contingency Salad offers reliable performance and awful design",
    "sku": "B73QZLVOT8",
    "brand": "Koch Group",
    "category": "Clothing",
    "price": 417.55,
    "price_min": 386.55,
    "stock": 103,
    "color": "orange",
    "size": "Large",
    "image_url": "https://images.unsplash.com/photo-1583743814966-8936f5b7be1a?crop=entropy&cs=tinysrgb&fit=max&fm=jpg&ixid=M3w4MDQ0NzJ8MHwxfHNlYXJjaHw1fHxTaGlydHxlbnwwfHx8fDE3NTc5NDk1NTF8MA&ixlib=rb-4.1.0&q=80&w=400"
  },
  {
    "name": "Awesome Desk",
    "description": "Discover the dental new Fish with an exciting mix of Plastic ingredients",
    "sku": "MTYBDOUL5V",
    "brand": "Conn Inc",
    "category": "Furniture",
    "price": 1954.25,
    "price_min": 1929.25,
    "stock": 75,
    "color": "lavender",
    "size": "Medium",
    "image_url": "https://images.unsplash.com/photo-1518655048521-f130df041f66?crop=entropy&cs=tinysrgb&fit=max&fm=jpg&ixid=M3w4MDQ0NzJ8MHwxfHNlYXJjaHwxfHxEZXNrfGVufDB8fHx8MTc1Nzk0OTU1MXww&ixlib=rb-4.1.0&q=80&w=400"
  },
  {
    "name": "Refined Table",
    "description": "New Hat model with 32 GB RAM, 214 GB storage, and stunning features",
    "sku": "UNH1R6V0PF",
    "brand": "Hansen, West and Kunze",
    "category": "Furniture",
    "price": 231.69,
    "price_min": 193.69,
    "stock": 49,
    "color": "fuchsia",
    "size": "Small",
    "image_url": "https://images.unsplash.com/photo-1576506542790-51244b486a6b?crop=entropy&cs=tinysrgb&fit=max&fm=jpg&ixid=M3w4MDQ0NzJ8MHwxfHNlYXJjaHwxNHx8VGFibGV8ZW58MHx8fHwxNzU3OTQ5NTUxfDA&ixlib=rb-4.1.0&q=80&w=400"
  },
  {
    "name": "Ergonomic Microwave",
    "description": "Innovative Car featuring dental technology and Concrete construction",
    "sku": "QL3TEI14PT",
    "brand": "Trantow Inc",
    "category": "Electronics & Home Appliances",
    "price": 1409.75,
    "price_min": 1401.75,
    "stock": 333,
    "color": "tan",
    "size": "Medium",
    "image_url": "https://images.unsplash.com/photo-1677470749785-865d577ef881?crop=entropy&cs=tinysrgb&fit=max&fm=jpg&ixid=M3w4MDQ0NzJ8MHwxfHNlYXJjaHwxN3x8TWljcm93YXZlfGVufDB8fHx8MTc1Nzk0OTU1MXww&ixlib=rb-4.1.0&q=80&w=400"
  },
  {
    "name": "Elegant Dress",
    "description": "Harvey - Fisher's most advanced Chips technology increases nifty capabilities",
    "sku": "D8PTKNLKB3",
    "brand": "Ferry, Greenholt and Hand",
    "category": "Clothing",
    "price": 1693.4,
    "price_min": 1644.4,
    "stock": 375,
    "color": "azure",
    "size": "Small",
    "image_url": "https://images.unsplash.com/photo-1519554318711-aaf73ece6ff9?crop=entropy&cs=tinysrgb&fit=max&fm=jpg&ixid=M3w4MDQ0NzJ8MHwxfHNlYXJjaHwxMnx8RHJlc3N8ZW58MHx8fHwxNzU3OTQ5NTUxfDA&ixlib=rb-4.1.0&q=80&w=400"
  },
  {
    "name": "Sleek Microwave",
    "description": "Innovative Computer featuring alienated technology and Marble construction",
    "sku": "OCGE73AGWK",
    "brand": "VonRueden Group",
    "category": "Electronics & Home Appliances",
    "price": 380.39,
    "price_min": 345.39,
    "stock": 384,
    "color": "red",
    "size": "Medium",
    "image_url": "https://images.unsplash.com/photo-1596552183299-000ef779e88d?crop=entropy&cs=tinysrgb&fit=max&fm=jpg&ixid=M3w4MDQ0NzJ8MHwxfHNlYXJjaHw3fHxNaWNyb3dhdmV8ZW58MHx8fHwxNzU3OTQ5NTUxfDA&ixlib=rb-4.1.0&q=80&w=400"
  },
  {
    "name": "Handcrafted Microwave",
    "description": "Professional-grade Pizza perfect for selfish training and recreational use",
    "sku": "XYBWV3UQZU",
    "brand": "O'Conner, Romaguera and Sanford",
    "category": "Electronics & Home Appliances",
    "price": 154.39,
    "price_min": 140.39,
    "stock": 240,
    "color": "tan",
    "size": "Large",
    "image_url": "https://images.unsplash.com/photo-1696814543707-1bdce2a5d48e?crop=entropy&cs=tinysrgb&fit=max&fm=jpg&ixid=M3w4MDQ0NzJ8MHwxfHNlYXJjaHw5fHxNaWNyb3dhdmV8ZW58MHx8fHwxNzU3OTQ5NTUxfDA&ixlib=rb-4.1.0&q=80&w=400"
  },
  {
    "name": "Licensed Jacket",
    "description": "Discover the zebra-like agility of our Table, perfect for poor users",
    "sku": "GOG8E00UCX",
    "brand": "Little LLC",
    "category": "Clothing",
    "price": 577.59,
    "price_min": 541.59,
    "stock": 151,
    "color": "orange",
    "size": "Large",
    "image_url": "https://images.unsplash.com/photo-1543274747-e969ff86c466?crop=entropy&cs=tinysrgb&fit=max&fm=jpg&ixid=M3w4MDQ0NzJ8MHwxfHNlYXJjaHwxNXx8SmFja2V0fGVufDB8fHx8MTc1Nzk0OTU1MXww&ixlib=rb-4.1.0&q=80&w=400"
  },
  {
    "name": "Unbranded Microwave",
    "description": "Introducing the Tuvalu-inspired Tuna, blending profuse style with local craftsmanship",
    "sku": "P4T2TICN1M",
    "brand": "Koss - Kulas",
    "category": "Electronics & Home Appliances",
    "price": 249.19,
    "price_min": 244.19,
    "stock": 454,
    "color": "orchid",
    "size": "Small",
    "image_url": "https://images.unsplash.com/photo-1629935309001-a7bd2ddec5fb?crop=entropy&cs=tinysrgb&fit=max&fm=jpg&ixid=M3w4MDQ0NzJ8MHwxfHNlYXJjaHwxMHx8TWljcm93YXZlfGVufDB8fHx8MTc1Nzk0OTU1MXww&ixlib=rb-4.1.0&q=80&w=400"
  },
  {
    "name": "Gorgeous Sofa",
    "description": "Introducing the Italy-inspired Pizza, blending nifty style with local craftsmanship",
    "sku": "JRV3NVBKVS",
    "brand": "Jones, Pouros and Lockman",
    "category": "Furniture",
    "price": 1072.55,
    "price_min": 1062.55,
    "stock": 163,
    "color": "azure",
    "size": "Small",
    "image_url": "https://images.unsplash.com/photo-1634497885778-152eb6fd543d?crop=entropy&cs=tinysrgb&fit=max&fm=jpg&ixid=M3w4MDQ0NzJ8MHwxfHNlYXJjaHwxN3x8U29mYXxlbnwwfHx8fDE3NTc5NDk1NTF8MA&ixlib=rb-4.1.0&q=80&w=400"
  },
  {
    "name": "Sleek Table",
    "description": "The Webster Cheese is the latest in a series of orderly products from Kuvalis and Sons",
    "sku": "JAE79BA7IS",
    "brand": "Auer, Pouros and Sporer",
    "category": "Furniture",
    "price": 1262.15,
    "price_min": 1226.15,
    "stock": 374,
    "color": "plum",
    "size": "Medium",
    "image_url": "https://images.unsplash.com/photo-1577017077260-0f6fef54ec0c?crop=entropy&cs=tinysrgb&fit=max&fm=jpg&ixid=M3w4MDQ0NzJ8MHwxfHNlYXJjaHwyMHx8VGFibGV8ZW58MHx8fHwxNzU3OTQ5NTUxfDA&ixlib=rb-4.1.0&q=80&w=400"
  },
  {
    "name": "Modern Jacket",
    "description": "Our savory-inspired Cheese brings a taste of luxury to your trained lifestyle",
    "sku": "68X5ED8UMV",
    "brand": "VonRueden, Satterfield and Strosin",
    "category": "Clothing",
    "price": 1809.69,
    "price_min": 1793.69,
    "stock": 207,
    "color": "plum",
    "size": "Large",
    "image_url": "https://images.unsplash.com/photo-1611312449408-fcece27cdbb7?crop=entropy&cs=tinysrgb&fit=max&fm=jpg&ixid=M3w4MDQ0NzJ8MHwxfHNlYXJjaHw0fHxKYWNrZXR8ZW58MHx8fHwxNzU3OTQ5NTUxfDA&ixlib=rb-4.1.0&q=80&w=400"
  },
  {
    "name": "Electronic Pants",
    "description": "Frozen Tuna designed with Aluminum for shoddy performance",
    "sku": "WQZ8SPKXHW",
    "brand": "Schmeler - Schultz",
    "category": "Clothing",
    "price": 267.05,
    "price_min": 220.05,
    "stock": 13,
    "color": "salmon",
    "size": "Medium",
    "image_url": "https://images.unsplash.com/photo-1506629082955-511b1aa562c8?crop=entropy&cs=tinysrgb&fit=max&fm=jpg&ixid=M3w4MDQ0NzJ8MHwxfHNlYXJjaHw0fHxQYW50c3xlbnwwfHx8fDE3NTc5NDk1NTF8MA&ixlib=rb-4.1.0&q=80&w=400"
  },
  {
    "name": "Oriental Desk",
    "description": "Small Tuna designed with Metal for criminal performance",
    "sku": "7QSN7GO123",
    "brand": "Hyatt, Stark and VonRueden",
    "category": "Furniture",
    "price": 1958.69,
    "price_min": 1942.69,
    "stock": 33,
    "color": "azure",
    "size": "Small",
    "image_url": "https://images.unsplash.com/photo-1611269154421-4e27233ac5c7?crop=entropy&cs=tinysrgb&fit=max&fm=jpg&ixid=M3w4MDQ0NzJ8MHwxfHNlYXJjaHw4fHxEZXNrfGVufDB8fHx8MTc1Nzk0OTU1MXww&ixlib=rb-4.1.0&q=80&w=400"
  },
  {
    "name": "Bespoke Desk",
    "description": "Russel and Sons's most advanced Hat technology increases brave capabilities",
    "sku": "48N9TG6IDU",
    "brand": "Balistreri - Wisozk",
    "category": "Furniture",
    "price": 1176.49,
    "price_min": 1145.49,
    "stock": 67,
    "color": "black",
    "size": "Medium",
    "image_url": "https://images.unsplash.com/photo-1500989145603-8e7ef71d639e?crop=entropy&cs=tinysrgb&fit=max&fm=jpg&ixid=M3w4MDQ0NzJ8MHwxfHNlYXJjaHw5fHxEZXNrfGVufDB8fHx8MTc1Nzk0OTU1MXww&ixlib=rb-4.1.0&q=80&w=400"
  },
  {
    "name": "Bespoke Refrigerator",
    "description": "Professional-grade Table perfect for putrid training and recreational use",
    "sku": "7EBHTOKG3B",
    "brand": "Nicolas, Emmerich and Kutch",
    "category": "Electronics & Home Appliances",
    "price": 1218.5,
    "price_min": 1176.5,
    "stock": 273,
    "color": "fuchsia",
    "size": "Medium",
    "image_url": "https://images.unsplash.com/photo-1722603929403-de9e80c46a9a?crop=entropy&cs=tinysrgb&fit=max&fm=jpg&ixid=M3w4MDQ0NzJ8MHwxfHNlYXJjaHwxM3x8UmVmcmlnZXJhdG9yfGVufDB8fHx8MTc1Nzk0OTU1MXww&ixlib=rb-4.1.0&q=80&w=400"
  },
  {
    "name": "Rustic Dress",
    "description": "New azure Pizza with ergonomic design for vague comfort",
    "sku": "VL1GRS6W2T",
    "brand": "Fisher - Schowalter",
    "category": "Clothing",
    "price": 451.05,
    "price_min": 416.05,
    "stock": 227,
    "color": "cyan",
    "size": "Large",
    "image_url": "https://images.unsplash.com/photo-1623609163859-ca93c959b98a?crop=entropy&cs=tinysrgb&fit=max&fm=jpg&ixid=M3w4MDQ0NzJ8MHwxfHNlYXJjaHw1fHxEcmVzc3xlbnwwfHx8fDE3NTc5NDk1NTF8MA&ixlib=rb-4.1.0&q=80&w=400"
  },
  {
    "name": "Bespoke Chair",
    "description": "The Vicenta Pants is the latest in a series of arid products from Bartoletti Inc",
    "sku": "TZOEZW3W4C",
    "brand": "Wehner - Satterfield",
    "category": "Furniture",
    "price": 1836.39,
    "price_min": 1808.39,
    "stock": 192,
    "color": "plum",
    "size": "Medium",
    "image_url": "https://images.unsplash.com/photo-1586023492125-27b2c045efd7?crop=entropy&cs=tinysrgb&fit=max&fm=jpg&ixid=M3w4MDQ0NzJ8MHwxfHNlYXJjaHwxNHx8Q2hhaXJ8ZW58MHx8fHwxNzU3OTQ5NTUxfDA&ixlib=rb-4.1.0&q=80&w=400"
  },
  {
    "name": "Generic Jacket",
    "description": "The Stuart Hat is the latest in a series of clean products from O'Kon LLC",
    "sku": "B5RRDGERXW",
    "brand": "Little, Hackett and Reilly",
    "category": "Clothing",
    "price": 953.1,
    "price_min": 928.1,
    "stock": 273,
    "color": "salmon",
    "size": "Medium",
    "image_url": "https://images.unsplash.com/photo-1618329918461-51bb072e0ea5?crop=entropy&cs=tinysrgb&fit=max&fm=jpg&ixid=M3w4MDQ0NzJ8MHwxfHNlYXJjaHwxMnx8SmFja2V0fGVufDB8fHx8MTc1Nzk0OTU1MXww&ixlib=rb-4.1.0&q=80&w=400"
  },
  {
    "name": "Small Jacket",
    "description": "The blue Shoes combines United States Minor Outlying Islands aesthetics with Manganese-based durability",
    "sku": "C5RUO2WWSA",
    "brand": "Strosin LLC",
    "category": "Clothing",
    "price": 1729.79,
    "price_min": 1718.79,
    "stock": 302,
    "color": "white",
    "size": "Large",
    "image_url": "https://images.unsplash.com/photo-1627637454030-5ddd536e06e5?crop=entropy&cs=tinysrgb&fit=max&fm=jpg&ixid=M3w4MDQ0NzJ8MHwxfHNlYXJjaHw5fHxKYWNrZXR8ZW58MHx8fHwxNzU3OTQ5NTUxfDA&ixlib=rb-4.1.0&q=80&w=400"
  },
  {
    "name": "Gorgeous Table",
    "description": "Savor the tender essence in our Gloves, designed for stingy culinary adventures",
    "sku": "CN72ETP6R3",
    "brand": "Beier and Sons",
    "category": "Furniture",
    "price": 1653.45,
    "price_min": 1630.45,
    "stock": 352,
    "color": "lime",
    "size": "Medium",
    "image_url": "https://images.unsplash.com/photo-1491336440196-6d4fee45a05e?crop=entropy&cs=tinysrgb&fit=max&fm=jpg&ixid=M3w4MDQ0NzJ8MHwxfHNlYXJjaHwxMXx8VGFibGV8ZW58MHx8fHwxNzU3OTQ5NTUxfDA&ixlib=rb-4.1.0&q=80&w=400"
  },
  {
    "name": "Soft Jacket",
    "description": "New azure Chips with ergonomic design for fruitful comfort",
    "sku": "B9I6HYPCJR",
    "brand": "Hammes and Sons",
    "category": "Clothing",
    "price": 272.19,
    "price_min": 264.19,
    "stock": 207,
    "color": "orange",
    "size": "Large",
    "image_url": "https://images.unsplash.com/photo-1543076447-215ad9ba6923?crop=entropy&cs=tinysrgb&fit=max&fm=jpg&ixid=M3w4MDQ0NzJ8MHwxfHNlYXJjaHw1fHxKYWNrZXR8ZW58MHx8fHwxNzU3OTQ5NTUxfDA&ixlib=rb-4.1.0&q=80&w=400"
  },
  {
    "name": "Generic Refrigerator",
    "description": "The May Chicken is the latest in a series of gifted products from Legros - Stark",
    "sku": "2B3OXNAM6J",
    "brand": "Swaniawski Group",
    "category": "Electronics & Home Appliances",
    "price": 1189.15,
    "price_min": 1169.15,
    "stock": 33,
    "color": "fuchsia",
    "size": "Medium",
    "image_url": "https://images.unsplash.com/photo-1610733374054-59454fe657cd?crop=entropy&cs=tinysrgb&fit=max&fm=jpg&ixid=M3w4MDQ0NzJ8MHwxfHNlYXJjaHwxOHx8UmVmcmlnZXJhdG9yfGVufDB8fHx8MTc1Nzk0OTU1MXww&ixlib=rb-4.1.0&q=80&w=400"
  },
  {
    "name": "Modern Laptop",
    "description": "Innovative Cheese featuring remarkable technology and Metal construction",
    "sku": "RY26KW78XV",
    "brand": "Dibbert, Blanda and Nikolaus",
    "category": "Electronics & Home Appliances",
    "price": 184.55,
    "price_min": 159.55,
    "stock": 460,
    "color": "violet",
    "size": "Small",
    "image_url": "https://images.unsplash.com/photo-1531297484001-80022131f5a1?crop=entropy&cs=tinysrgb&fit=max&fm=jpg&ixid=M3w4MDQ0NzJ8MHwxfHNlYXJjaHwxMXx8TGFwdG9wfGVufDB8fHx8MTc1Nzk0OTU1MXww&ixlib=rb-4.1.0&q=80&w=400"
  },
  {
    "name": "Awesome Table",
    "description": "Stylish Chips designed to make you stand out with shameful looks",
    "sku": "9LKGNN50C5",
    "brand": "Buckridge, Stanton and Kris",
    "category": "Furniture",
    "price": 1235.39,
    "price_min": 1228.39,
    "stock": 446,
    "color": "plum",
    "size": "Small",
    "image_url": "https://images.unsplash.com/photo-1565791380713-1756b9a05343?crop=entropy&cs=tinysrgb&fit=max&fm=jpg&ixid=M3w4MDQ0NzJ8MHwxfHNlYXJjaHw0fHxUYWJsZXxlbnwwfHx8fDE3NTc5NDk1NTF8MA&ixlib=rb-4.1.0&q=80&w=400"
  },
  {
    "name": "Refined Pants",
    "description": "Rustic Salad designed with Bamboo for short-term performance",
    "sku": "WDE0OAZSQ0",
    "brand": "Nader and Sons",
    "category": "Clothing",
    "price": 1832.09,
    "price_min": 1822.09,
    "stock": 254,
    "color": "black",
    "size": "Small",
    "image_url": "https://images.unsplash.com/photo-1634564235572-cd6f37694266?crop=entropy&cs=tinysrgb&fit=max&fm=jpg&ixid=M3w4MDQ0NzJ8MHwxfHNlYXJjaHwxOXx8UGFudHN8ZW58MHx8fHwxNzU3OTQ5NTUxfDA&ixlib=rb-4.1.0&q=80&w=400"
  },
  {
    "name": "Rustic Table",
    "description": "Experience the mint green brilliance of our Sausages, perfect for glorious environments",
    "sku": "OT3D8N8VAD",
    "brand": "Grady and Sons",
    "category": "Furniture",
    "price": 168.75,
    "price_min": 124.75,
    "stock": 351,
    "color": "maroon",
    "size": "Medium",
    "image_url": "https://images.unsplash.com/photo-1594125674956-61a9b49c8ecc?crop=entropy&cs=tinysrgb&fit=max&fm=jpg&ixid=M3w4MDQ0NzJ8MHwxfHNlYXJjaHw1fHxUYWJsZXxlbnwwfHx8fDE3NTc5NDk1NTF8MA&ixlib=rb-4.1.0&q=80&w=400"
  },
  {
    "name": "Frozen Table",
    "description": "Introducing the Lithuania-inspired Salad, blending rundown style with local craftsmanship",
    "sku": "I62BXB7U59",
    "brand": "Kuhn LLC",
    "category": "Furniture",
    "price": 1996.09,
    "price_min": 1975.09,
    "stock": 278,
    "color": "pink",
    "size": "Medium",
    "image_url": "https://images.unsplash.com/photo-1485431142439-206ba3a9383e?crop=entropy&cs=tinysrgb&fit=max&fm=jpg&ixid=M3w4MDQ0NzJ8MHwxfHNlYXJjaHwxM3x8VGFibGV8ZW58MHx8fHwxNzU3OTQ5NTUxfDA&ixlib=rb-4.1.0&q=80&w=400"
  },
  {
    "name": "Electronic Bed",
    "description": "The Catalina Table is the latest in a series of same products from Will, Moen and Larkin",
    "sku": "GZBLQKBYH6",
    "brand": "Will, Marquardt and Ziemann",
    "category": "Furniture",
    "price": 1598.19,
    "price_min": 1569.19,
    "stock": 175,
    "color": "magenta",
    "size": "Medium",
    "image_url": "https://images.unsplash.com/photo-1536349788264-1b816db3cc13?crop=entropy&cs=tinysrgb&fit=max&fm=jpg&ixid=M3w4MDQ0NzJ8MHwxfHNlYXJjaHwzfHxCZWR8ZW58MHx8fHwxNzU3OTQ5NTUxfDA&ixlib=rb-4.1.0&q=80&w=400"
  },
  {
    "name": "Licensed Dress",
    "description": "Discover the aggravating new Ball with an exciting mix of Gold ingredients",
    "sku": "IA9S7WHSZ6",
    "brand": "Yost - Ryan",
    "category": "Clothing",
    "price": 1588.19,
    "price_min": 1549.19,
    "stock": 417,
    "color": "purple",
    "size": "Small",
    "image_url": "https://images.unsplash.com/flagged/photo-1585052201332-b8c0ce30972f?crop=entropy&cs=tinysrgb&fit=max&fm=jpg&ixid=M3w4MDQ0NzJ8MHwxfHNlYXJjaHwxfHxEcmVzc3xlbnwwfHx8fDE3NTc5NDk1NTF8MA&ixlib=rb-4.1.0&q=80&w=400"
  },
  {
    "name": "Handcrafted Jacket",
    "description": "Ruecker, Purdy and Weissnat's most advanced Towels technology increases esteemed capabilities",
    "sku": "IY4K9I1L17",
    "brand": "Deckow - Durgan",
    "category": "Clothing",
    "price": 1220.52,
    "price_min": 1211.52,
    "stock": 28,
    "color": "orchid",
    "size": "Medium",
    "image_url": "https://images.unsplash.com/photo-1532704102644-883111bdf82d?crop=entropy&cs=tinysrgb&fit=max&fm=jpg&ixid=M3w4MDQ0NzJ8MHwxfHNlYXJjaHwxMXx8SmFja2V0fGVufDB8fHx8MTc1Nzk0OTU1MXww&ixlib=rb-4.1.0&q=80&w=400"
  },
  {
    "name": "Sleek Chair",
    "description": "Innovative Cheese featuring sparse technology and Plastic construction",
    "sku": "M791V10UHJ",
    "brand": "O'Keefe - Bradtke",
    "category": "Furniture",
    "price": 1481.89,
    "price_min": 1438.89,
    "stock": 232,
    "color": "white",
    "size": "Medium",
    "image_url": "https://images.unsplash.com/photo-1519947486511-46149fa0a254?crop=entropy&cs=tinysrgb&fit=max&fm=jpg&ixid=M3w4MDQ0NzJ8MHwxfHNlYXJjaHw3fHxDaGFpcnxlbnwwfHx8fDE3NTc5NDk1NTF8MA&ixlib=rb-4.1.0&q=80&w=400"
  },
  {
    "name": "Bespoke Dress",
    "description": "Featuring Barium-enhanced technology, our Keyboard offers unparalleled wry performance",
    "sku": "V5W095W753",
    "brand": "Schmidt - Hane",
    "category": "Clothing",
    "price": 369.49,
    "price_min": 364.49,
    "stock": 296,
    "color": "orchid",
    "size": "Small",
    "image_url": "https://images.unsplash.com/photo-1559034750-cdab70a66b8e?crop=entropy&cs=tinysrgb&fit=max&fm=jpg&ixid=M3w4MDQ0NzJ8MHwxfHNlYXJjaHwxN3x8RHJlc3N8ZW58MHx8fHwxNzU3OTQ5NTUxfDA&ixlib=rb-4.1.0&q=80&w=400"
  },
  {
    "name": "Frozen Sofa",
    "description": "Introducing the Slovenia-inspired Hat, blending unfit style with local craftsmanship",
    "sku": "KVLC3BB3YP",
    "brand": "Lueilwitz - Bruen",
    "category": "Furniture",
    "price": 1323.09,
    "price_min": 1308.09,
    "stock": 419,
    "color": "olive",
    "size": "Medium",
    "image_url": "https://images.unsplash.com/photo-1555041469-a586c61ea9bc?crop=entropy&cs=tinysrgb&fit=max&fm=jpg&ixid=M3w4MDQ0NzJ8MHwxfHNlYXJjaHwxfHxTb2ZhfGVufDB8fHx8MTc1Nzk0OTU1MXww&ixlib=rb-4.1.0&q=80&w=400"
  },
  {
    "name": "Soft Bed",
    "description": "Ergonomic Pizza made with Gold for all-day aggravating support",
    "sku": "T1WMY7OXGA",
    "brand": "Osinski - Kutch",
    "category": "Furniture",
    "price": 725.6,
    "price_min": 690.6,
    "stock": 227,
    "color": "blue",
    "size": "Large",
    "image_url": "https://images.unsplash.com/photo-1582582621959-48d27397dc69?crop=entropy&cs=tinysrgb&fit=max&fm=jpg&ixid=M3w4MDQ0NzJ8MHwxfHNlYXJjaHwxNnx8QmVkfGVufDB8fHx8MTc1Nzk0OTU1MXww&ixlib=rb-4.1.0&q=80&w=400"
  },
  {
    "name": "Ergonomic Camera",
    "description": "Experience the sky blue brilliance of our Chair, perfect for alienated environments",
    "sku": "LOE4KWXPZG",
    "brand": "Littel, Pfeffer and Schimmel",
    "category": "Electronics & Home Appliances",
    "price": 961.64,
    "price_min": 928.64,
    "stock": 156,
    "color": "lavender",
    "size": "Medium",
    "image_url": "https://images.unsplash.com/photo-1580707221190-bd94d9087b7f?crop=entropy&cs=tinysrgb&fit=max&fm=jpg&ixid=M3w4MDQ0NzJ8MHwxfHNlYXJjaHwxNXx8Q2FtZXJhfGVufDB8fHx8MTc1Nzk0OTU1Mnww&ixlib=rb-4.1.0&q=80&w=400"
  },
  {
    "name": "Incredible Dress",
    "description": "Our penguin-friendly Ball ensures super comfort for your pets",
    "sku": "SC4M70F6BH",
    "brand": "Botsford Inc",
    "category": "Clothing",
    "price": 1858.35,
    "price_min": 1818.35,
    "stock": 21,
    "color": "green",
    "size": "Medium",
    "image_url": "https://images.unsplash.com/photo-1618932260643-eee4a2f652a6?crop=entropy&cs=tinysrgb&fit=max&fm=jpg&ixid=M3w4MDQ0NzJ8MHwxfHNlYXJjaHw0fHxEcmVzc3xlbnwwfHx8fDE3NTc5NDk1NTF8MA&ixlib=rb-4.1.0&q=80&w=400"
  },
  {
    "name": "Intelligent Table",
    "description": "Lemke, Crist and Johnston's most advanced Sausages technology increases unselfish capabilities",
    "sku": "HIW1F7F4YV",
    "brand": "Reinger Inc",
    "category": "Furniture",
    "price": 1128.81,
    "price_min": 1118.81,
    "stock": 66,
    "color": "red",
    "size": "Large",
    "image_url": "https://images.unsplash.com/photo-1523247297454-ef69fd04e051?crop=entropy&cs=tinysrgb&fit=max&fm=jpg&ixid=M3w4MDQ0NzJ8MHwxfHNlYXJjaHw3fHxUYWJsZXxlbnwwfHx8fDE3NTc5NDk1NTF8MA&ixlib=rb-4.1.0&q=80&w=400"
  },
  {
    "name": "Oriental Table",
    "description": "Bartoletti, Crooks and Kohler's most advanced Salad technology increases nimble capabilities",
    "sku": "9QSAVX65OF",
    "brand": "Beahan, Beier and Carroll",
    "category": "Furniture",
    "price": 633.99,
    "price_min": 590.99,
    "stock": 341,
    "color": "olive",
    "size": "Small",
    "image_url": "https://images.unsplash.com/photo-1495548054858-0e78bb72869e?crop=entropy&cs=tinysrgb&fit=max&fm=jpg&ixid=M3w4MDQ0NzJ8MHwxfHNlYXJjaHwxN3x8VGFibGV8ZW58MHx8fHwxNzU3OTQ5NTUxfDA&ixlib=rb-4.1.0&q=80&w=400"
  },
  {
    "name": "Ergonomic Dress",
    "description": "Experience the olive brilliance of our Keyboard, perfect for earnest environments",
    "sku": "IF3RBLES6I",
    "brand": "West, Prohaska and Wuckert",
    "category": "Clothing",
    "price": 1036.19,
    "price_min": 987.19,
    "stock": 169,
    "color": "violet",
    "size": "Small",
    "image_url": "https://images.unsplash.com/photo-1612722432474-b971cdcea546?crop=entropy&cs=tinysrgb&fit=max&fm=jpg&ixid=M3w4MDQ0NzJ8MHwxfHNlYXJjaHwxNnx8RHJlc3N8ZW58MHx8fHwxNzU3OTQ5NTUxfDA&ixlib=rb-4.1.0&q=80&w=400"
  },
  {
    "name": "Elegant TV",
    "description": "Discover the questionable new Gloves with an exciting mix of Wooden ingredients",
    "sku": "TJATSZHURA",
    "brand": "Farrell, O'Conner and Swaniawski",
    "category": "Electronics & Home Appliances",
    "price": 1036.69,
    "price_min": 1007.69,
    "stock": 170,
    "color": "salmon",
    "size": "Small",
    "image_url": "https://images.unsplash.com/photo-1509281373149-e957c6296406?crop=entropy&cs=tinysrgb&fit=max&fm=jpg&ixid=M3w4MDQ0NzJ8MHwxfHNlYXJjaHwyfHxUVnxlbnwwfHx8fDE3NTc5NDk1NTF8MA&ixlib=rb-4.1.0&q=80&w=400"
  },
  {
    "name": "Modern Microwave",
    "description": "The Ottis Table is the latest in a series of perky products from Conroy, Schimmel and Boyer",
    "sku": "9QOLXFSMH5",
    "brand": "Reichert Inc",
    "category": "Electronics & Home Appliances",
    "price": 1549.24,
    "price_min": 1534.24,
    "stock": 436,
    "color": "azure",
    "size": "Large",
    "image_url": "https://images.unsplash.com/photo-1693786229416-2dd310137f18?crop=entropy&cs=tinysrgb&fit=max&fm=jpg&ixid=M3w4MDQ0NzJ8MHwxfHNlYXJjaHwyfHxNaWNyb3dhdmV8ZW58MHx8fHwxNzU3OTQ5NTUxfDA&ixlib=rb-4.1.0&q=80&w=400"
  },
  {
    "name": "Intelligent Camera",
    "description": "Savor the tender essence in our Car, designed for aged culinary adventures",
    "sku": "7VTK0OYAS3",
    "brand": "Nader LLC",
    "category": "Electronics & Home Appliances",
    "price": 676.09,
    "price_min": 648.09,
    "stock": 397,
    "color": "fuchsia",
    "size": "Large",
    "image_url": "https://images.unsplash.com/photo-1616088886430-ccd86fef0713?crop=entropy&cs=tinysrgb&fit=max&fm=jpg&ixid=M3w4MDQ0NzJ8MHwxfHNlYXJjaHwxOXx8Q2FtZXJhfGVufDB8fHx8MTc1Nzk0OTU1Mnww&ixlib=rb-4.1.0&q=80&w=400"
  },
  {
    "name": "Unbranded Chair",
    "description": "The maroon Towels combines Brunei Darussalam aesthetics with Protactinium-based durability",
    "sku": "EE2RMR6YQS",
    "brand": "Mertz Inc",
    "category": "Furniture",
    "price": 1118.89,
    "price_min": 1094.89,
    "stock": 354,
    "color": "tan",
    "size": "Small",
    "image_url": "https://images.unsplash.com/photo-1580480055273-228ff5388ef8?crop=entropy&cs=tinysrgb&fit=max&fm=jpg&ixid=M3w4MDQ0NzJ8MHwxfHNlYXJjaHw4fHxDaGFpcnxlbnwwfHx8fDE3NTc5NDk1NTF8MA&ixlib=rb-4.1.0&q=80&w=400"
  },
  {
    "name": "Frozen Pants",
    "description": "Discover the variable new Mouse with an exciting mix of Plastic ingredients",
    "sku": "3QYXI9JUL4",
    "brand": "Bartell, Christiansen and Schulist",
    "category": "Clothing",
    "price": 943.95,
    "price_min": 920.95,
    "stock": 103,
    "color": "silver",
    "size": "Small",
    "image_url": "https://images.unsplash.com/photo-1602293589930-45aad59ba3ab?crop=entropy&cs=tinysrgb&fit=max&fm=jpg&ixid=M3w4MDQ0NzJ8MHwxfHNlYXJjaHw2fHxQYW50c3xlbnwwfHx8fDE3NTc5NDk1NTF8MA&ixlib=rb-4.1.0&q=80&w=400"
  },
  {
    "name": "Elegant Shirt",
    "description": "Professional-grade Bacon perfect for infinite training and recreational use",
    "sku": "4LCRI6LMEC",
    "brand": "Lindgren and Sons",
    "category": "Clothing",
    "price": 159.79,
    "price_min": 146.79,
    "stock": 12,
    "color": "black",
    "size": "Small",
    "image_url": "https://images.unsplash.com/photo-1598032895397-b9472444bf93?crop=entropy&cs=tinysrgb&fit=max&fm=jpg&ixid=M3w4MDQ0NzJ8MHwxfHNlYXJjaHwxNHx8U2hpcnR8ZW58MHx8fHwxNzU3OTQ5NTUxfDA&ixlib=rb-4.1.0&q=80&w=400"
  },
  {
    "name": "Fresh Dress",
    "description": "The olive Shoes combines Tokelau aesthetics with Fluorine-based durability",
    "sku": "CGTWWT8MBS",
    "brand": "Kub - Hartmann",
    "category": "Clothing",
    "price": 455.89,
    "price_min": 408.89,
    "stock": 318,
    "color": "fuchsia",
    "size": "Medium",
    "image_url": "https://images.unsplash.com/photo-1595777457583-95e059d581b8?crop=entropy&cs=tinysrgb&fit=max&fm=jpg&ixid=M3w4MDQ0NzJ8MHwxfHNlYXJjaHwyfHxEcmVzc3xlbnwwfHx8fDE3NTc5NDk1NTF8MA&ixlib=rb-4.1.0&q=80&w=400"
  },
  {
    "name": "Awesome Shoes",
    "description": "The pink Mouse combines Cote d'Ivoire aesthetics with Flerovium-based durability",
    "sku": "AG28SFQZ3B",
    "brand": "Murray, Jakubowski and Feeney",
    "category": "Clothing",
    "price": 1988.3,
    "price_min": 1969.3,
    "stock": 324,
    "color": "blue",
    "size": "Small",
    "image_url": "https://images.unsplash.com/photo-1551107696-a4b0c5a0d9a2?crop=entropy&cs=tinysrgb&fit=max&fm=jpg&ixid=M3w4MDQ0NzJ8MHwxfHNlYXJjaHwxMHx8U2hvZXN8ZW58MHx8fHwxNzU3OTQ5NTUxfDA&ixlib=rb-4.1.0&q=80&w=400"
  },
  {
    "name": "Generic Bed",
    "description": "Discover the upset new Bike with an exciting mix of Plastic ingredients",
    "sku": "XI10GU8ME4",
    "brand": "Blanda, Greenfelder and Kunze",
    "category": "Furniture",
    "price": 1468.15,
    "price_min": 1429.15,
    "stock": 346,
    "color": "plum",
    "size": "Medium",
    "image_url": "https://images.unsplash.com/photo-1617325247661-675ab4b64ae2?crop=entropy&cs=tinysrgb&fit=max&fm=jpg&ixid=M3w4MDQ0NzJ8MHwxfHNlYXJjaHw2fHxCZWR8ZW58MHx8fHwxNzU3OTQ5NTUxfDA&ixlib=rb-4.1.0&q=80&w=400"
  },
  {
    "name": "Awesome Sofa",
    "description": "Experience the teal brilliance of our Pants, perfect for corrupt environments",
    "sku": "Q1ZX5UGOKN",
    "brand": "Murphy - Sporer",
    "category": "Furniture",
    "price": 319.39,
    "price_min": 300.39,
    "stock": 318,
    "color": "salmon",
    "size": "Small",
    "image_url": "https://images.unsplash.com/photo-1567016432779-094069958ea5?crop=entropy&cs=tinysrgb&fit=max&fm=jpg&ixid=M3w4MDQ0NzJ8MHwxfHNlYXJjaHwzfHxTb2ZhfGVufDB8fHx8MTc1Nzk0OTU1MXww&ixlib=rb-4.1.0&q=80&w=400"
  },
  {
    "name": "Tasty TV",
    "description": "The Kallie Soap is the latest in a series of decisive products from Smith, Lebsack and Wolf",
    "sku": "DSTL7KTRO7",
    "brand": "Keebler and Sons",
    "category": "Electronics & Home Appliances",
    "price": 520.19,
    "price_min": 490.19000000000005,
    "stock": 188,
    "color": "tan",
    "size": "Large",
    "image_url": "https://images.unsplash.com/photo-1567690187548-f07b1d7bf5a9?crop=entropy&cs=tinysrgb&fit=max&fm=jpg&ixid=M3w4MDQ0NzJ8MHwxfHNlYXJjaHw4fHxUVnxlbnwwfHx8fDE3NTc5NDk1NTF8MA&ixlib=rb-4.1.0&q=80&w=400"
  },
  {
    "name": "Unbranded Shirt",
    "description": "The white Tuna combines Switzerland aesthetics with Tantalum-based durability",
    "sku": "SPB1RSLL4R",
    "brand": "Langworth Group",
    "category": "Clothing",
    "price": 239.79,
    "price_min": 190.79,
    "stock": 198,
    "color": "tan",
    "size": "Large",
    "image_url": "https://images.unsplash.com/photo-1603252109303-2751441dd157?crop=entropy&cs=tinysrgb&fit=max&fm=jpg&ixid=M3w4MDQ0NzJ8MHwxfHNlYXJjaHw5fHxTaGlydHxlbnwwfHx8fDE3NTc5NDk1NTF8MA&ixlib=rb-4.1.0&q=80&w=400"
  },
  {
    "name": "Intelligent Microwave",
    "description": "Stylish Keyboard designed to make you stand out with curly looks",
    "sku": "XD761R2JBX",
    "brand": "Flatley Inc",
    "category": "Electronics & Home Appliances",
    "price": 1415.49,
    "price_min": 1391.49,
    "stock": 418,
    "color": "plum",
    "size": "Large",
    "image_url": "https://images.unsplash.com/photo-1584269600519-112d071b35e6?crop=entropy&cs=tinysrgb&fit=max&fm=jpg&ixid=M3w4MDQ0NzJ8MHwxfHNlYXJjaHwxM3x8TWljcm93YXZlfGVufDB8fHx8MTc1Nzk0OTU1MXww&ixlib=rb-4.1.0&q=80&w=400"
  },
  {
    "name": "Luxurious Sofa",
    "description": "Professional-grade Bacon perfect for rusty training and recreational use",
    "sku": "24JF0BLEHB",
    "brand": "Armstrong, Bashirian and Hoppe",
    "category": "Furniture",
    "price": 1460.59,
    "price_min": 1437.59,
    "stock": 470,
    "color": "violet",
    "size": "Medium",
    "image_url": "https://images.unsplash.com/photo-1573866926487-a1865558a9cf?crop=entropy&cs=tinysrgb&fit=max&fm=jpg&ixid=M3w4MDQ0NzJ8MHwxfHNlYXJjaHwxMnx8U29mYXxlbnwwfHx8fDE3NTc5NDk1NTF8MA&ixlib=rb-4.1.0&q=80&w=400"
  },
  {
    "name": "Rustic Pants",
    "description": "The sleek and uniform Chair comes with yellow LED lighting for smart functionality",
    "sku": "2APTPDMZ0S",
    "brand": "Hermiston - Bruen",
    "category": "Clothing",
    "price": 85.55,
    "price_min": 39.55,
    "stock": 413,
    "color": "cyan",
    "size": "Large",
    "image_url": "https://images.unsplash.com/photo-1590159983013-d4ff5fc71c1d?crop=entropy&cs=tinysrgb&fit=max&fm=jpg&ixid=M3w4MDQ0NzJ8MHwxfHNlYXJjaHwxNXx8UGFudHN8ZW58MHx8fHwxNzU3OTQ5NTUxfDA&ixlib=rb-4.1.0&q=80&w=400"
  },
  {
    "name": "Modern Bed",
    "description": "Our golden-inspired Ball brings a taste of luxury to your deep lifestyle",
    "sku": "35K0VLULQF",
    "brand": "Romaguera, Berge and Bartoletti",
    "category": "Furniture",
    "price": 57.99,
    "price_min": 29.990000000000002,
    "stock": 436,
    "color": "violet",
    "size": "Small",
    "image_url": "https://images.unsplash.com/photo-1615874959474-d609969a20ed?crop=entropy&cs=tinysrgb&fit=max&fm=jpg&ixid=M3w4MDQ0NzJ8MHwxfHNlYXJjaHwyMHx8QmVkfGVufDB8fHx8MTc1Nzk0OTU1MXww&ixlib=rb-4.1.0&q=80&w=400"
  },
  {
    "name": "Fantastic Desk",
    "description": "The grey Towels combines Chad aesthetics with Lanthanum-based durability",
    "sku": "553UVJQ7UW",
    "brand": "Ondricka - Conroy",
    "category": "Furniture",
    "price": 626.29,
    "price_min": 589.29,
    "stock": 203,
    "color": "indigo",
    "size": "Large",
    "image_url": "https://images.unsplash.com/photo-1486946255434-2466348c2166?crop=entropy&cs=tinysrgb&fit=max&fm=jpg&ixid=M3w4MDQ0NzJ8MHwxfHNlYXJjaHwyMHx8RGVza3xlbnwwfHx8fDE3NTc5NDk1NTF8MA&ixlib=rb-4.1.0&q=80&w=400"
  },
  {
    "name": "Rustic Laptop",
    "description": "Ergonomic Cheese made with Metal for all-day timely support",
    "sku": "NT5PMNZ1K8",
    "brand": "Mraz, Boyer and Tremblay",
    "category": "Electronics & Home Appliances",
    "price": 377.96,
    "price_min": 367.96,
    "stock": 200,
    "color": "cyan",
    "size": "Large",
    "image_url": "https://images.unsplash.com/photo-1484788984921-03950022c9ef?crop=entropy&cs=tinysrgb&fit=max&fm=jpg&ixid=M3w4MDQ0NzJ8MHwxfHNlYXJjaHw0fHxMYXB0b3B8ZW58MHx8fHwxNzU3OTQ5NTUxfDA&ixlib=rb-4.1.0&q=80&w=400"
  },
  {
    "name": "Fresh Microwave",
    "description": "The Persistent interactive model Salad offers reliable performance and shy design",
    "sku": "74AYKIC9IW",
    "brand": "Douglas Inc",
    "category": "Electronics & Home Appliances",
    "price": 116.05,
    "price_min": 84.05,
    "stock": 499,
    "color": "salmon",
    "size": "Medium",
    "image_url": "https://images.unsplash.com/photo-1723259461381-59ab9fa18f5d?crop=entropy&cs=tinysrgb&fit=max&fm=jpg&ixid=M3w4MDQ0NzJ8MHwxfHNlYXJjaHwxMXx8TWljcm93YXZlfGVufDB8fHx8MTc1Nzk0OTU1MXww&ixlib=rb-4.1.0&q=80&w=400"
  },
  {
    "name": "Ergonomic Table",
    "description": "The Cross-platform discrete system engine Pants offers reliable performance and complicated design",
    "sku": "4G0Y1F495G",
    "brand": "Wuckert, Mertz and Barton",
    "category": "Furniture",
    "price": 191.95,
    "price_min": 184.95,
    "stock": 322,
    "color": "black",
    "size": "Small",
    "image_url": "https://images.unsplash.com/32/Mc8kW4x9Q3aRR3RkP5Im_IMG_4417.jpg?crop=entropy&cs=tinysrgb&fit=max&fm=jpg&ixid=M3w4MDQ0NzJ8MHwxfHNlYXJjaHw4fHxUYWJsZXxlbnwwfHx8fDE3NTc5NDk1NTF8MA&ixlib=rb-4.1.0&q=80&w=400"
  },
  {
    "name": "Electronic Sofa",
    "description": "Featuring Bohrium-enhanced technology, our Fish offers unparalleled agile performance",
    "sku": "3OELAYKOWK",
    "brand": "Dooley, Larson and Schoen",
    "category": "Furniture",
    "price": 1372.19,
    "price_min": 1351.19,
    "stock": 67,
    "color": "fuchsia",
    "size": "Small",
    "image_url": "https://images.unsplash.com/photo-1529943892821-2f04b070cd2f?crop=entropy&cs=tinysrgb&fit=max&fm=jpg&ixid=M3w4MDQ0NzJ8MHwxfHNlYXJjaHwyMHx8U29mYXxlbnwwfHx8fDE3NTc5NDk1NTF8MA&ixlib=rb-4.1.0&q=80&w=400"
  },
  {
    "name": "Frozen Camera",
    "description": "The Reid Computer is the latest in a series of showy products from Cremin Inc",
    "sku": "2RXUARKNXZ",
    "brand": "Von Group",
    "category": "Electronics & Home Appliances",
    "price": 1287.29,
    "price_min": 1272.29,
    "stock": 194,
    "color": "orange",
    "size": "Large",
    "image_url": "https://images.unsplash.com/photo-1460134846237-51c777df6111?crop=entropy&cs=tinysrgb&fit=max&fm=jpg&ixid=M3w4MDQ0NzJ8MHwxfHNlYXJjaHwxMHx8Q2FtZXJhfGVufDB8fHx8MTc1Nzk0OTU1Mnww&ixlib=rb-4.1.0&q=80&w=400"
  },
  {
    "name": "Recycled Pants",
    "description": "Our fresh-inspired Fish brings a taste of luxury to your hot lifestyle",
    "sku": "WU7BRC9AW1",
    "brand": "Sipes - Kautzer",
    "category": "Clothing",
    "price": 960,
    "price_min": 936,
    "stock": 144,
    "color": "pink",
    "size": "Large",
    "image_url": "https://images.unsplash.com/photo-1714729382668-7bc3bb261662?crop=entropy&cs=tinysrgb&fit=max&fm=jpg&ixid=M3w4MDQ0NzJ8MHwxfHNlYXJjaHwxMHx8UGFudHN8ZW58MHx8fHwxNzU3OTQ5NTUxfDA&ixlib=rb-4.1.0&q=80&w=400"
  },
  {
    "name": "Awesome Laptop",
    "description": "Our rich-inspired Soap brings a taste of luxury to your willing lifestyle",
    "sku": "I0HZA2M48R",
    "brand": "Runolfsdottir, Bergstrom and King",
    "category": "Electronics & Home Appliances",
    "price": 592.39,
    "price_min": 556.39,
    "stock": 0,
    "color": "turquoise",
    "size": "Small",
    "image_url": "https://images.unsplash.com/photo-1649972904349-6e44c42644a7?crop=entropy&cs=tinysrgb&fit=max&fm=jpg&ixid=M3w4MDQ0NzJ8MXwxfHNlYXJjaHwxfHxMYXB0b3B8ZW58MHx8fHwxNzU3OTQ5NTUxfDA&ixlib=rb-4.1.0&q=80&w=400"
  },
  {
    "name": "Awesome Jacket",
    "description": "Professional-grade Chair perfect for good-natured training and recreational use",
    "sku": "HUU4HVPNMS",
    "brand": "Morar Group",
    "category": "Clothing",
    "price": 878.89,
    "price_min": 836.89,
    "stock": 62,
    "color": "blue",
    "size": "Large",
    "image_url": "https://images.unsplash.com/photo-1591047139829-d91aecb6caea?crop=entropy&cs=tinysrgb&fit=max&fm=jpg&ixid=M3w4MDQ0NzJ8MHwxfHNlYXJjaHwxfHxKYWNrZXR8ZW58MHx8fHwxNzU3OTQ5NTUxfDA&ixlib=rb-4.1.0&q=80&w=400"
  },
  {
    "name": "Rustic TV",
    "description": "The Toy Chair is the latest in a series of salty products from Robel, Jones and Langosh",
    "sku": "DIYRPX0RK5",
    "brand": "Reinger - Bernier",
    "category": "Electronics & Home Appliances",
    "price": 1166.75,
    "price_min": 1148.75,
    "stock": 441,
    "color": "grey",
    "size": "Medium",
    "image_url": "https://images.unsplash.com/photo-1573399054516-90665ecc44be?crop=entropy&cs=tinysrgb&fit=max&fm=jpg&ixid=M3w4MDQ0NzJ8MHwxfHNlYXJjaHwxOHx8VFZ8ZW58MHx8fHwxNzU3OTQ5NTUxfDA&ixlib=rb-4.1.0&q=80&w=400"
  },
  {
    "name": "Unbranded Table",
    "description": "Jenkins, Stark and Dibbert's most advanced Salad technology increases linear capabilities",
    "sku": "OBAIL0B91C",
    "brand": "Fahey, Sauer and Ledner",
    "category": "Furniture",
    "price": 731.29,
    "price_min": 726.29,
    "stock": 64,
    "color": "olive",
    "size": "Medium",
    "image_url": "https://images.unsplash.com/photo-1600623050499-84929aad17c9?crop=entropy&cs=tinysrgb&fit=max&fm=jpg&ixid=M3w4MDQ0NzJ8MHwxfHNlYXJjaHw2fHxUYWJsZXxlbnwwfHx8fDE3NTc5NDk1NTF8MA&ixlib=rb-4.1.0&q=80&w=400"
  },
  {
    "name": "Elegant Pants",
    "description": "New maroon Gloves with ergonomic design for big comfort",
    "sku": "DBWSKN6M4N",
    "brand": "Harris - Watsica",
    "category": "Clothing",
    "price": 396.29,
    "price_min": 362.29,
    "stock": 45,
    "color": "red",
    "size": "Small",
    "image_url": "https://images.unsplash.com/photo-1718252540511-e958742e4165?crop=entropy&cs=tinysrgb&fit=max&fm=jpg&ixid=M3w4MDQ0NzJ8MHwxfHNlYXJjaHwxMnx8UGFudHN8ZW58MHx8fHwxNzU3OTQ5NTUxfDA&ixlib=rb-4.1.0&q=80&w=400"
  },
  {
    "name": "Awesome Camera",
    "description": "The blue Sausages combines Greenland aesthetics with Americium-based durability",
    "sku": "SD8XIHJIFG",
    "brand": "Howe LLC",
    "category": "Electronics & Home Appliances",
    "price": 1300.09,
    "price_min": 1262.09,
    "stock": 35,
    "color": "white",
    "size": "Medium",
    "image_url": "https://images.unsplash.com/photo-1452780212940-6f5c0d14d848?crop=entropy&cs=tinysrgb&fit=max&fm=jpg&ixid=M3w4MDQ0NzJ8MHwxfHNlYXJjaHwxNnx8Q2FtZXJhfGVufDB8fHx8MTc1Nzk0OTU1Mnww&ixlib=rb-4.1.0&q=80&w=400"
  },
  {
    "name": "Luxurious Shirt",
    "description": "Ergonomic Ball made with Gold for all-day joyful support",
    "sku": "TETW303KIT",
    "brand": "Crona - Schmitt",
    "category": "Clothing",
    "price": 1735.59,
    "price_min": 1686.59,
    "stock": 448,
    "color": "olive",
    "size": "Small",
    "image_url": "https://images.unsplash.com/photo-1598033129183-c4f50c736f10?crop=entropy&cs=tinysrgb&fit=max&fm=jpg&ixid=M3w4MDQ0NzJ8MHwxfHNlYXJjaHwxN3x8U2hpcnR8ZW58MHx8fHwxNzU3OTQ5NTUxfDA&ixlib=rb-4.1.0&q=80&w=400"
  },
  {
    "name": "Modern Pants",
    "description": "Discover the giraffe-like agility of our Hat, perfect for different users",
    "sku": "JQCBE6XBA2",
    "brand": "Beer - Hettinger",
    "category": "Clothing",
    "price": 130.39,
    "price_min": 96.38999999999999,
    "stock": 193,
    "color": "blue",
    "size": "Large",
    "image_url": "https://images.unsplash.com/photo-1541099649105-f69ad21f3246?crop=entropy&cs=tinysrgb&fit=max&fm=jpg&ixid=M3w4MDQ0NzJ8MHwxfHNlYXJjaHwxMXx8UGFudHN8ZW58MHx8fHwxNzU3OTQ5NTUxfDA&ixlib=rb-4.1.0&q=80&w=400"
  },
  {
    "name": "Luxurious Refrigerator",
    "description": "Generic Chips designed with Aluminum for talkative performance",
    "sku": "V47YV6TUW6",
    "brand": "Cronin, Boyle and Feest",
    "category": "Electronics & Home Appliances",
    "price": 1782.89,
    "price_min": 1750.89,
    "stock": 113,
    "color": "gold",
    "size": "Large",
    "image_url": "https://images.unsplash.com/photo-1721563927724-74b1a0ddef33?crop=entropy&cs=tinysrgb&fit=max&fm=jpg&ixid=M3w4MDQ0NzJ8MHwxfHNlYXJjaHwxMnx8UmVmcmlnZXJhdG9yfGVufDB8fHx8MTc1Nzk0OTU1MXww&ixlib=rb-4.1.0&q=80&w=400"
  },
  {
    "name": "Practical Chair",
    "description": "The Centralized full-range model Computer offers reliable performance and rectangular design",
    "sku": "CTN18IT331",
    "brand": "Bogisich Inc",
    "category": "Furniture",
    "price": 376.45,
    "price_min": 327.45,
    "stock": 169,
    "color": "purple",
    "size": "Large",
    "image_url": "https://images.unsplash.com/photo-1517705008128-361805f42e86?crop=entropy&cs=tinysrgb&fit=max&fm=jpg&ixid=M3w4MDQ0NzJ8MHwxfHNlYXJjaHwxOHx8Q2hhaXJ8ZW58MHx8fHwxNzU3OTQ5NTUxfDA&ixlib=rb-4.1.0&q=80&w=400"
  },
  {
    "name": "Fresh Desk",
    "description": "The Centralized asymmetric complexity Sausages offers reliable performance and substantial design",
    "sku": "QNWWELWC7J",
    "brand": "King - Hills",
    "category": "Furniture",
    "price": 1035.19,
    "price_min": 992.19,
    "stock": 57,
    "color": "black",
    "size": "Medium",
    "image_url": "https://images.unsplash.com/photo-1487017159836-4e23ece2e4cf?crop=entropy&cs=tinysrgb&fit=max&fm=jpg&ixid=M3w4MDQ0NzJ8MHwxfHNlYXJjaHwxMHx8RGVza3xlbnwwfHx8fDE3NTc5NDk1NTF8MA&ixlib=rb-4.1.0&q=80&w=400"
  },
  {
    "name": "Sleek Bed",
    "description": "The Extended analyzing projection Pants offers reliable performance and tragic design",
    "sku": "9IX5XS2VZX",
    "brand": "Koelpin - Hirthe",
    "category": "Furniture",
    "price": 1841.14,
    "price_min": 1820.14,
    "stock": 306,
    "color": "pink",
    "size": "Medium",
    "image_url": "https://images.unsplash.com/photo-1505693416388-ac5ce068fe85?crop=entropy&cs=tinysrgb&fit=max&fm=jpg&ixid=M3w4MDQ0NzJ8MHwxfHNlYXJjaHwyfHxCZWR8ZW58MHx8fHwxNzU3OTQ5NTUxfDA&ixlib=rb-4.1.0&q=80&w=400"
  },
  {
    "name": "Electronic Desk",
    "description": "Innovative Bike featuring guilty technology and Aluminum construction",
    "sku": "1F9DHZ0IID",
    "brand": "Moen, Dibbert and Kuvalis",
    "category": "Furniture",
    "price": 151.6,
    "price_min": 124.6,
    "stock": 214,
    "color": "white",
    "size": "Medium",
    "image_url": "https://images.unsplash.com/photo-1526566762798-8fac9c07aa98?crop=entropy&cs=tinysrgb&fit=max&fm=jpg&ixid=M3w4MDQ0NzJ8MHwxfHNlYXJjaHwxOXx8RGVza3xlbnwwfHx8fDE3NTc5NDk1NTF8MA&ixlib=rb-4.1.0&q=80&w=400"
  },
  {
    "name": "Modern Dress",
    "description": "Stylish Chicken designed to make you stand out with cooperative looks",
    "sku": "5NQ3T9QAM5",
    "brand": "Rice - Rolfson",
    "category": "Clothing",
    "price": 72.85,
    "price_min": 35.849999999999994,
    "stock": 401,
    "color": "silver",
    "size": "Large",
    "image_url": "https://images.unsplash.com/photo-1533659828870-95ee305cee3e?crop=entropy&cs=tinysrgb&fit=max&fm=jpg&ixid=M3w4MDQ0NzJ8MHwxfHNlYXJjaHwxNXx8RHJlc3N8ZW58MHx8fHwxNzU3OTQ5NTUxfDA&ixlib=rb-4.1.0&q=80&w=400"
  },
  {
    "name": "Refined Refrigerator",
    "description": "The Kathryn Pants is the latest in a series of giving products from Nicolas - Koelpin",
    "sku": "NLYVN9FX5O",
    "brand": "Williamson - Mayert",
    "category": "Electronics & Home Appliances",
    "price": 593.25,
    "price_min": 550.25,
    "stock": 148,
    "color": "teal",
    "size": "Large",
    "image_url": "https://images.unsplash.com/photo-1710947949965-8150d227d337?crop=entropy&cs=tinysrgb&fit=max&fm=jpg&ixid=M3w4MDQ0NzJ8MHwxfHNlYXJjaHw1fHxSZWZyaWdlcmF0b3J8ZW58MHx8fHwxNzU3OTQ5NTUxfDA&ixlib=rb-4.1.0&q=80&w=400"
  }
]